<record>
	<header>
		<identifier>oai:rijksmuseum.nl/collection:RP-T-1953-257</identifier>
		<datestamp>2012-10-26T13:43:55Z</datestamp>
	</header>
	<metadata>
		<oai_dc:dc>
			<dc:format>https://www.rijksmuseum.nl/assetimage2.jsp?id=RP-T-1953-257</dc:format>
			<dc:format>https://www.rijksmuseum.nl/nl/collectie/RP-T-1953-257</dc:format>
			<dc:identifier>RP-T-1953-257</dc:identifier>
			<dc:identifier>RM0001.COLLECT.238727</dc:identifier>
			<dc:language>Dutch</dc:language>
			<dc:publisher>Rijksmuseum</dc:publisher>
			<dc:rights>http://creativecommons.org/publicdomain/zero/1.0/</dc:rights>
			<dc:date>1748 -  1748</dc:date>
			<dc:format>hoogte 172 MMmmmm</dc:format>
			<dc:format>breedte 221 MMmmmm</dc:format>
			<dc:format>materiaal: papier</dc:format>
			<dc:format>materiaal: waterverf</dc:format>
			<dc:format>techniek: aquarelleren</dc:format>
			<dc:format>techniek: potlood</dc:format>
			<dc:format>techniek: pen in grijs</dc:format>
			<dc:format>techniek: penseel in grijs</dc:format>
			<dc:format>techniek: penseel in waterverf in kleuren</dc:format>
			<dc:creator>vermeld op object tekenaar: Pronk, Cornelis</dc:creator>
			<dc:coverage/>
			<dc:type>tekening</dc:type>
			<dc:title>IJsvermaak op een bevroren vaart</dc:title>
			<dc:coverage>tweede kwart 18e eeuw</dc:coverage>
			<dc:subject>Iconclasscode: 25H213</dc:subject>
			<dc:subject>Iconclasscode: 43C244</dc:subject>
			<dc:subject>Iconclasscode: 26D</dc:subject>
		</oai_dc:dc>
	</metadata>
</record>
