<record>
	<header>
		<identifier>oai:rijksmuseum.nl/collection:RP-T-1890-A-2354</identifier>
		<datestamp>2012-10-26T13:47:40Z</datestamp>
	</header>
	<metadata>
		<oai_dc:dc>
			<dc:format>https://www.rijksmuseum.nl/assetimage2.jsp?id=RP-T-1890-A-2354</dc:format>
			<dc:format>https://www.rijksmuseum.nl/nl/collectie/RP-T-1890-A-2354</dc:format>
			<dc:identifier>RP-T-1890-A-2354</dc:identifier>
			<dc:identifier>RM0001.COLLECT.242689</dc:identifier>
			<dc:language>Dutch</dc:language>
			<dc:publisher>Rijksmuseum</dc:publisher>
			<dc:rights>http://creativecommons.org/publicdomain/zero/1.0/</dc:rights>
			<dc:date>1700 -  1800</dc:date>
			<dc:format>hoogte 403 MMmmmm</dc:format>
			<dc:format>breedte 555 MMmmmm</dc:format>
			<dc:format>materiaal: papier</dc:format>
			<dc:format>techniek: zwart en wit krijt</dc:format>
			<dc:creator> tekenaar: anoniem</dc:creator>
			<dc:coverage/>
			<dc:creator> naar tekening van: Saftleven, Herman</dc:creator>
			<dc:coverage/>
			<dc:type>tekening</dc:type>
			<dc:title>Ruiters met takkenbossen op een landweg bij een vervallen gebouw</dc:title>
			<dc:subject>Iconclasscode: 25H</dc:subject>
			<dc:subject>Iconclasscode: 25I9</dc:subject>
			<dc:subject>Iconclasscode: 46C11</dc:subject>
		</oai_dc:dc>
	</metadata>
</record>
